onlinejudge_bundle/__init__.py
onlinejudge_bundle/main.py
onlinejudge_verify/__init__.py
onlinejudge_verify/config.py
onlinejudge_verify/main.py
onlinejudge_verify/marker.py
onlinejudge_verify/utils.py
onlinejudge_verify/verify.py
onlinejudge_verify/documentation/__init__.py
onlinejudge_verify/documentation/build.py
onlinejudge_verify/documentation/configure.py
onlinejudge_verify/documentation/front_matter.py
onlinejudge_verify/documentation/main.py
onlinejudge_verify/documentation/type.py
onlinejudge_verify/languages/__init__.py
onlinejudge_verify/languages/cplusplus.py
onlinejudge_verify/languages/cplusplus_bundle.py
onlinejudge_verify/languages/csharpscript.py
onlinejudge_verify/languages/go.py
onlinejudge_verify/languages/haskell.py
onlinejudge_verify/languages/java.py
onlinejudge_verify/languages/list.py
onlinejudge_verify/languages/models.py
onlinejudge_verify/languages/nim.py
onlinejudge_verify/languages/python.py
onlinejudge_verify/languages/ruby.py
onlinejudge_verify/languages/rust.py
onlinejudge_verify/languages/special_comments.py
onlinejudge_verify/languages/user_defined.py
onlinejudge_verify_resources/Gemfile
onlinejudge_verify_resources/__init__.py
onlinejudge_verify_resources/_config.yml
onlinejudge_verify_resources/_includes/__init__.py
onlinejudge_verify_resources/_includes/document_body.html
onlinejudge_verify_resources/_includes/document_footer.html
onlinejudge_verify_resources/_includes/document_header.html
onlinejudge_verify_resources/_includes/highlight.html
onlinejudge_verify_resources/_includes/mathjax.html
onlinejudge_verify_resources/_includes/theme_fix.html
onlinejudge_verify_resources/_includes/toppage_body.html
onlinejudge_verify_resources/_includes/toppage_header.html
onlinejudge_verify_resources/_layouts/__init__.py
onlinejudge_verify_resources/_layouts/document.html
onlinejudge_verify_resources/_layouts/page.html
onlinejudge_verify_resources/_layouts/toppage.html
onlinejudge_verify_resources/assets/site-header.txt
online_judge_verify_helper-5.6.0.dist-info/LICENSE
online_judge_verify_helper-5.6.0.dist-info/METADATA
online_judge_verify_helper-5.6.0.dist-info/WHEEL
online_judge_verify_helper-5.6.0.dist-info/entry_points.txt
online_judge_verify_helper-5.6.0.dist-info/top_level.txt
online_judge_verify_helper-5.6.0.dist-info/RECORD
