Metadata-Version: 2.1
Name: online-judge-verify-helper
Version: 5.6.0
Summary: UNKNOWN
Home-page: https://github.com/kmyk/online-judge-verify-helper
Author: Kimiyuki Onaka
Author-email: kimiyuki95@gmail.com
License: MIT License
Platform: UNKNOWN
Classifier: Development Status :: 5 - Production/Stable
Classifier: Environment :: Console
Classifier: Intended Audience :: Developers
Classifier: License :: OSI Approved :: MIT License
Classifier: Operating System :: OS Independent
Classifier: Programming Language :: Python :: 3.5
Classifier: Programming Language :: Python :: 3.6
Classifier: Topic :: Internet :: WWW/HTTP
Classifier: Topic :: Software Development
Classifier: Topic :: Utilities
Requires-Python: >=3.6
Requires-Dist: colorlog
Requires-Dist: pyyaml
Requires-Dist: online-judge-tools (>=11.3.0)
Requires-Dist: setuptools
Requires-Dist: toml
Requires-Dist: importlab
Provides-Extra: dev
Requires-Dist: isort (==5.5.2) ; extra == 'dev'
Requires-Dist: mypy (==0.782) ; extra == 'dev'
Requires-Dist: pylint (==2.6.0) ; extra == 'dev'
Requires-Dist: yapf (==0.30.0) ; extra == 'dev'
